ZhihuWendaMeiyouDaoshiDeZhidaoYanjiushengRuheYueduWenxianTichuChuangjianXieLunwen/README.md
ZhihuWendaMeiyouDaoshiDeZhidaoYanjiushengRuheYueduWenxianTichuChuangjianXieLunwen/__init__.py
ZhihuWendaMeiyouDaoshiDeZhidaoYanjiushengRuheYueduWenxianTichuChuangjianXieLunwen/__main__.py
ZhihuWendaMeiyouDaoshiDeZhidaoYanjiushengRuheYueduWenxianTichuChuangjianXieLunwen/file.epub
ZhihuWendaMeiyouDaoshiDeZhidaoYanjiushengRuheYueduWenxianTichuChuangjianXieLunwen/index.html
ZhihuWendaMeiyouDaoshiDeZhidaoYanjiushengRuheYueduWenxianTichuChuangjianXieLunwen/css/__init__.py
ZhihuWendaMeiyouDaoshiDeZhidaoYanjiushengRuheYueduWenxianTichuChuangjianXieLunwen/css/annotations.css
ZhihuWendaMeiyouDaoshiDeZhidaoYanjiushengRuheYueduWenxianTichuChuangjianXieLunwen/css/main.css
ZhihuWendaMeiyouDaoshiDeZhidaoYanjiushengRuheYueduWenxianTichuChuangjianXieLunwen/css/normalize.css
ZhihuWendaMeiyouDaoshiDeZhidaoYanjiushengRuheYueduWenxianTichuChuangjianXieLunwen/css/popup.css
ZhihuWendaMeiyouDaoshiDeZhidaoYanjiushengRuheYueduWenxianTichuChuangjianXieLunwen/font/__init__.py
ZhihuWendaMeiyouDaoshiDeZhidaoYanjiushengRuheYueduWenxianTichuChuangjianXieLunwen/font/fontello.eot
ZhihuWendaMeiyouDaoshiDeZhidaoYanjiushengRuheYueduWenxianTichuChuangjianXieLunwen/font/fontello.svg
ZhihuWendaMeiyouDaoshiDeZhidaoYanjiushengRuheYueduWenxianTichuChuangjianXieLunwen/font/fontello.ttf
ZhihuWendaMeiyouDaoshiDeZhidaoYanjiushengRuheYueduWenxianTichuChuangjianXieLunwen/font/fontello.woff
ZhihuWendaMeiyouDaoshiDeZhidaoYanjiushengRuheYueduWenxianTichuChuangjianXieLunwen/img/__init__.py
ZhihuWendaMeiyouDaoshiDeZhidaoYanjiushengRuheYueduWenxianTichuChuangjianXieLunwen/img/annotator-glyph-sprite.png
ZhihuWendaMeiyouDaoshiDeZhidaoYanjiushengRuheYueduWenxianTichuChuangjianXieLunwen/img/annotator-icon-sprite.png
ZhihuWendaMeiyouDaoshiDeZhidaoYanjiushengRuheYueduWenxianTichuChuangjianXieLunwen/img/apple-touch-icon.png
ZhihuWendaMeiyouDaoshiDeZhidaoYanjiushengRuheYueduWenxianTichuChuangjianXieLunwen/img/cancelfullscreen.png
zhihu_wenda_meiyou_daoshi_de_zhidao_yanjiusheng_ruhe_yuedu_wenxian_tichu_chuangjian_xie_lunwen-2024.3.5.0.dist-info/METADATA
zhihu_wenda_meiyou_daoshi_de_zhidao_yanjiusheng_ruhe_yuedu_wenxian_tichu_chuangjian_xie_lunwen-2024.3.5.0.dist-info/WHEEL
zhihu_wenda_meiyou_daoshi_de_zhidao_yanjiusheng_ruhe_yuedu_wenxian_tichu_chuangjian_xie_lunwen-2024.3.5.0.dist-info/entry_points.txt
zhihu_wenda_meiyou_daoshi_de_zhidao_yanjiusheng_ruhe_yuedu_wenxian_tichu_chuangjian_xie_lunwen-2024.3.5.0.dist-info/top_level.txt
zhihu_wenda_meiyou_daoshi_de_zhidao_yanjiusheng_ruhe_yuedu_wenxian_tichu_chuangjian_xie_lunwen-2024.3.5.0.dist-info/RECORD
