Metadata-Version: 2.1
Name: zhihu-wenda-meiyou-daoshi-de-zhidao-yanjiusheng-ruhe-yuedu-wenxian-tichu-chuangjian-xie-lunwen
Version: 2024.3.5.0
Summary: 知乎问答：没有导师的指导，研究生如何阅读文献、提出创见、写论文？
Home-page: https://github.com/apachecn/zhihu-wenda-meiyou-daoshi-de-zhidao-yanjiusheng-ruhe-yuedu-wenxian-tichu-chuangjian-xie-lunwen
Author: ApacheCN
Author-email: apachecn@163.com
Classifier: Development Status :: 4 - Beta
Classifier: Environment :: Console
Classifier: Intended Audience :: Developers
Classifier: Intended Audience :: End Users/Desktop
Classifier: License :: Other/Proprietary License
Classifier: Natural Language :: Chinese (Simplified)
Classifier: Natural Language :: English
Classifier: Operating System :: OS Independent
Classifier: Programming Language :: Python :: 3
Classifier: Programming Language :: Python :: 3 :: Only
Classifier: Programming Language :: Python :: 3.6
Classifier: Programming Language :: Python :: 3.7
Classifier: Topic :: Text Processing :: Markup :: Markdown
Classifier: Topic :: Text Processing :: Markup :: HTML
Classifier: Topic :: Internet :: WWW/HTTP
Classifier: Topic :: Software Development :: Documentation
Classifier: Topic :: Documentation
Requires-Python: >=3.6
